quickforex/__init__.py
quickforex/api.py
quickforex/command_line.py
quickforex/domain.py
quickforex/errors.py
quickforex/http_requester.py
quickforex/logger.py
quickforex/utils.py
quickforex/providers/__init__.py
quickforex/providers/base.py
quickforex/providers/dummy.py
quickforex/providers/exchangerate_host.py
quickforex/providers/factory.py
quickforex/providers/provider_metadata.py
quickforex-0.1.3.dist-info/LICENSE
quickforex-0.1.3.dist-info/METADATA
quickforex-0.1.3.dist-info/WHEEL
quickforex-0.1.3.dist-info/entry_points.txt
quickforex-0.1.3.dist-info/top_level.txt
quickforex-0.1.3.dist-info/RECORD
